fattrace/__init__.py
fattrace-0.0.3.dist-info/licenses/LICENSE
fattrace-0.0.3.dist-info/METADATA
fattrace-0.0.3.dist-info/WHEEL
fattrace-0.0.3.dist-info/top_level.txt
fattrace-0.0.3.dist-info/RECORD
