Metadata-Version: 2.4
Name: fattrace
Version: 0.0.3
Summary: Informative Stacktrace that shows everything on the stack
Author-email: Masataro Asai <guicho271828@gmail.com>
License-Expression: MIT
Project-URL: Homepage, https://github.com/guicho271828/fattrace
Project-URL: Issues, https://github.com/guicho271828/fattrace/issues
Classifier: Development Status :: 5 - Production/Stable
Classifier: Environment :: Console
Classifier: Programming Language :: Python :: 3
Requires-Python: >=3.9
License-File: LICENSE
Requires-Dist: ansicolors
Provides-Extra: dev
Requires-Dist: pdm>=2.24.0; extra == "dev"
Requires-Dist: mypy; extra == "dev"
Requires-Dist: mypy-extensions; extra == "dev"
Requires-Dist: build; extra == "dev"
Requires-Dist: twine; extra == "dev"
Dynamic: license-file
